sccx/__init__.py
sccx-1.1.dist-info/METADATA
sccx-1.1.dist-info/RECORD
sccx-1.1.dist-info/WHEEL
sccx-1.1.dist-info/entry_points.txt
sccx-1.1.dist-info/top_level.txt
