Metadata-Version: 2.1
Name: sccx
Version: 1.1
Summary: A Great cheat cheet and a quick reference command line tool
Home-page: https://github.com/ziyadsk/scc
Author: Ziyadsk
Author-email: Ziyadkader@outlook.com
License: UNKNOWN
Platform: UNKNOWN
Classifier: Programming Language :: Python :: 3
Classifier: License :: OSI Approved :: MIT License
Classifier: Operating System :: OS Independent
